acheron/__init__.py
acheron/agent_sdk.py
acheron/client.py
acheron/py.typed
acheron_sdk-1.0.0.dist-info/licenses/LICENSE
acheron_sdk-1.0.0.dist-info/METADATA
acheron_sdk-1.0.0.dist-info/WHEEL
acheron_sdk-1.0.0.dist-info/top_level.txt
acheron_sdk-1.0.0.dist-info/RECORD
